Workbook
Name Slicer_Category: #N/A
Name Slicer_Category1: #N/A
Name Slicer_City: #N/A
Name Slicer_City1: #N/A
Name Slicer_Delivery_Status: #N/A
Name Slicer_Delivery_Status1: #N/A
Name Slicer_Payment_Mode: #N/A
Name Slicer_Payment_Mode1: #N/A

Sheet Product Analysis
A2: 1. Which category has highest sales? | C2: 2. Which product sold most? | G2: 3. Top 5 products by sales | J2: 4. Average unit price by category
A3: Row Labels | B3: Sum of Sales_Amount | D3: Row Labels | E3: Sum of Quantity | G3: Row Labels | H3: Sum of Sales_Amount | J3: Row Labels | K3: Average of Unit_Price
A4: Accessories | B4: 2549837.5 | D4: Shoes | E4: 78 | G4: Backpack | H4: 1638622.9 | J4: Accessories | K4: 23176.488
A5: Electronics | B5: 4003751.9 | D5: Backpack | E5: 76 | G5: Headphones | H5: 1402800.7 | J5: Electronics | K5: 25156.552
A6: Fashion | B6: 3044049.2 | D6: Headphones | E6: 66 | G6: Laptop | H6: 1194217.6 | J6: Fashion | K6: 26278.16
A7: Travel | B7: 1638622.9 | D7: T-Shirt | E7: 65 | G7: Shoes | H7: 1821078.2 | J7: Travel | K7: 25251
A8: Wearables | B8: 1134891.4 | D8: Keyboard | E8: 65 | G8: T-Shirt | H8: 1222970.9 | J8: Wearables | K8: 24392.722
A9: Grand Total | B9: 12371153 | D9: Smartwatch | E9: 58 | G9: Grand Total | H9: 7279690.5 | J9: Grand Total | K9: 24973.63
D10: Camera | E10: 53
D11: Laptop | E11: 48
D12: Monitor | E12: 45 | G12: 5. Category contribution percentage
D13: Mobile | E13: 39 | G13: =CategorySales/TotalSales -> #NAME?
D14: Grand Total | E14: 593

Sheet City Analysis
A2: 1. Which city has highest sales? | D2: 2. Total orders by city | G2: 3. Average sales by city | J2: 4. City with maximum quantity sold
A3: Row Labels | B3: Sum of Sales_Amount | D3: Row Labels | E3: Count of Order_ID | G3: Row Labels | H3: Average of Sales_Amount | J3: Row Labels | K3: Sum of Quantity
A4: Madurai | B4: 2228986.6 | D4: Bangalore | E4: 26 | G4: Bangalore | H4: 52509.86 | J4: Bangalore | K4: 73
A5: Kolkata | B5: 2087869.4 | D5: Chennai | E5: 18 | G5: Chennai | H5: 77121.464 | J5: Chennai | K5: 54
A6: Delhi | B6: 1791971.8 | D6: Delhi | E6: 31 | G6: Delhi | H6: 57805.54 | J6: Delhi | K6: 87
A7: Pune | B7: 1671425.4 | D7: Hyderabad | E7: 17 | G7: Hyderabad | H7: 36244.729 | J7: Hyderabad | K7: 45
A8: Chennai | B8: 1388186.4 | D8: Kolkata | E8: 29 | G8: Kolkata | H8: 71995.498 | J8: Kolkata | K8: 97
A9: Bangalore | B9: 1365256.4 | D9: Madurai | E9: 31 | G9: Madurai | H9: 71902.794 | J9: Madurai | K9: 91
A10: Mumbai | B10: 1221296.6 | D10: Mumbai | E10: 20 | G10: Mumbai | H10: 61064.83 | J10: Mumbai | K10: 59
A11: Hyderabad | B11: 616160.4 | D11: Pune | E11: 28 | G11: Pune | H11: 59693.764 | J11: Pune | K11: 87
A12: Grand Total | B12: 12371153 | D12: Grand Total | E12: 200 | G12: Grand Total | H12: 61855.765 | J12: Grand Total | K12: 593

Sheet DELIVERY STATUS ANALYSIS
A2: 1. Count of Delivered vs Pending Orders | D2: 2. Which city has more pending deliveries? | J2: 3. Sales amount by delivery status
A3: Row Labels | B3: Count of Order_ID | D3: Count of Order_ID | E3: Column Labels | J3: Row Labels | K3: Sum of Sales_Amount
A4: Cancelled | B4: 63 | D4: Row Labels | E4: Cancelled | F4: Delivered | G4: Pending | H4: Grand Total | J4: Cancelled | K4: 3510091.8
A5: Delivered | B5: 72 | D5: Bangalore | E5: 6 | F5: 12 | G5: 8 | H5: 26 | J5: Delivered | K5: 4794071.8
A6: Pending | B6: 65 | D6: Chennai | E6: 4 | F6: 7 | G6: 7 | H6: 18 | J6: Pending | K6: 4066989.3
A7: Grand Total | B7: 200 | D7: Delhi | E7: 16 | F7: 10 | G7: 5 | H7: 31 | J7: Grand Total | K7: 12371153
D8: Hyderabad | E8: 4 | F8: 7 | G8: 6 | H8: 17
D9: Kolkata | E9: 5 | F9: 14 | G9: 10 | H9: 29
D10: Madurai | E10: 10 | F10: 12 | G10: 9 | H10: 31
D11: Mumbai | E11: 7 | F11: 3 | G11: 10 | H11: 20
D12: Pune | E12: 11 | F12: 7 | G12: 10 | H12: 28
D13: Grand Total | E13: 63 | F13: 72 | G13: 65 | H13: 200

Sheet PAYMENT MODE ANALYSIS
A2: 1. Most used payment mode | D2: 2. Payment mode contribution to sales | G2: 3. Payment mode percentage
A3: Row Labels | B3: Count of Order_ID | D3: Row Labels | E3: Sum of Sales_Amount | G3: =PaymentModeSales/TotalSales -> #NAME?
A4: Card | B4: 49 | D4: Card | E4: 2349959.7
A5: COD | B5: 52 | D5: COD | E5: 3547164.1
A6: Net Banking | B6: 46 | D6: Net Banking | E6: 2659915.4
A7: UPI | B7: 53 | D7: UPI | E7: 3814113.7
A8: Grand Total | B8: 200 | D8: Grand Total | E8: 12371153

Sheet  DISCOUNT ANALYSIS
A2: 2. Which category gives highest discount? | E2: Compare discount vs sales | J2: High discount products
A3: Row Labels | B3: Average of Discount_% | E3: Sum of Discount_% | F3: Sum of Sales_Amount | J3: Row Labels | K3: Sum of Discount_%
A4: Accessories | B4: 15.243902 | E4: 2905 | F4: 12371153 | J4: Shoes | K4: 445
A5: Electronics | B5: 13.432836 | J5: Grand Total | K5: 445
A6: Fashion | B6: 15.6
A7: Travel | B7: 13.125
A8: Wearables | B8: 15.833333
A9: Grand Total | B9: 14.525

Sheet TIME-BASED ANALYSIS
A2: 1. Monthly sales trend | L2: Monthly quantity sold
A3: Row Labels | B3: Sum of Sales_Amount | L3: Row Labels | M3: Sum of Quantity
A4: Jan | B4: 674943.65 | L4: Jan | M4: 42
A5: Feb | B5: 757304.2 | L5: Feb | M5: 31
A6: Mar | B6: 1118681.6 | L6: Mar | M6: 52
A7: Apr | B7: 607215.3 | L7: Apr | M7: 28
A8: May | B8: 1075377.7 | L8: May | M8: 57
A9: Jun | B9: 791408.8 | L9: Jun | M9: 41
A10: Jul | B10: 1062970.8 | L10: Jul | M10: 44
A11: Aug | B11: 712323.8 | L11: Aug | M11: 32
A12: Sep | B12: 844334.7 | L12: Sep | M12: 46
A13: Oct | B13: 1855775.6 | L13: Oct | M13: 85
A14: Nov | B14: 1380716.3 | L14: Nov | M14: 66
A15: Dec | B15: 1490100.5 | L15: Dec | M15: 69
A16: Grand Total | B16: 12371153 | L16: Grand Total | M16: 593
E18: Monthly order count | J18: Best performing month
E19: Row Labels | F19: Count of Order_ID | K19: Row Labels | L19: Sum of Sales_Amount
E20: Jan | F20: 15 | K20: Oct | L20: 1855775.6
E21: Feb | F21: 10 | K21: Dec | L21: 1490100.5
E22: Mar | F22: 18 | K22: Nov | L22: 1380716.3
E23: Apr | F23: 10 | K23: Mar | L23: 1118681.6
E24: May | F24: 20 | K24: May | L24: 1075377.7
E25: Jun | F25: 17 | K25: Jul | L25: 1062970.8
E26: Jul | F26: 13 | K26: Sep | L26: 844334.7
E27: Aug | F27: 13 | K27: Jun | L27: 791408.8
E28: Sep | F28: 15 | K28: Feb | L28: 757304.2
E29: Oct | F29: 26 | K29: Aug | L29: 712323.8
E30: Nov | F30: 21 | K30: Jan | L30: 674943.65
E31: Dec | F31: 22 | K31: Apr | L31: 607215.3
E32: Grand Total | F32: 200 | K32: Grand Total | L32: 12371153

Sheet Flipkart_Sales_Data
A1: Order_ID | B1: Order_Date | C1: Customer_ID | D1: City | E1: Product_Name | F1: Category | G1: Quantity | H1: Unit_Price | I1: Discount_% | J1: Sales_Amount | K1: Payment_Mode | L1: Delivery_Status | M1: CountBlank | N1: Check duplicate Order IDs | O1: Format Order Date | P1: Month Column | Q1: Year Column | R1: Sales Category | S1: Discount Type | T1: Delivery Result
A2: FK0001 | B2: 45783 | C2: 1029 | D2: Bangalore | E2: Mobile | F2: Electronics | G2: 1 | H2: 49098 | I2: 15 | J2: 41733.3 | K2: UPI | L2: Cancelled | M2: =COUNTBLANK(A:A) -> 1048375 | N2: =COUNTIF(A:A,A2) -> 1 | O2: DD-MM-YYYY | P2: =TEXT(B2,"MMM") -> May | Q2: =YEAR(B2) -> 2025 | R2: =IF(J2>5000,"High Sales",IF(J2>2000,"Medium Sales","Low Sales")) -> High Sales | S2: =IF(I2>=20,"High Discount","Low Discount") -> Low Discount | T2: =IF(L2="Delivered","Successful","Pending") -> Pending
A3: FK0002 | B3: 45674 | C3: 1004 | D3: Madurai | E3: T-Shirt | F3: Fashion | G3: 1 | H3: 39198 | I3: 20 | J3: 31358.4 | K3: Card | L3: Delivered | M3: =COUNTBLANK(A:A) -> 1048375 | N3: =COUNTIF(A:A,A2) -> 1 | O3: DD-MMM-YYYY | P3: =TEXT(B3,"MMM") -> Jan | R3: =IF(J3>5000,"High Sales",IF(J3>2000,"Medium Sales","Low Sales")) -> High Sales | S3: =IF(I3>=20,"High Discount","Low Discount") -> High Discount | T3: =IF(L3="Delivered","Successful","Pending") -> Successful
A4: FK0003 | B4: 45759 | C4: 1092 | D4: Pune | E4: T-Shirt | F4: Fashion | G4: 5 | H4: 2239 | I4: 25 | J4: 8396.25 | K4: Card | L4: Pending | P4: =TEXT(B4,"MMM") -> Apr | R4: =IF(J4>5000,"High Sales",IF(J4>2000,"Medium Sales","Low Sales")) -> High Sales | S4: =IF(I4>=20,"High Discount","Low Discount") -> High Discount | T4: =IF(L4="Delivered","Successful","Pending") -> Pending
A5: FK0004 | B5: 46015 | C5: 1055 | D5: Hyderabad | E5: Backpack | F5: Travel | G5: 3 | H5: 925 | I5: 10 | J5: 2497.5 | K5: COD | L5: Delivered | P5: =TEXT(B5,"MMM") -> Dec | R5: =IF(J5>5000,"High Sales",IF(J5>2000,"Medium Sales","Low Sales")) -> Medium Sales | S5: =IF(I5>=20,"High Discount","Low Discount") -> Low Discount | T5: =IF(L5="Delivered","Successful","Pending") -> Successful
A6: FK0005 | B6: 45852 | C6: 1013 | D6: Hyderabad | E6: Smartwatch | F6: Wearables | G6: 3 | H6: 7198 | I6: 5 | J6: 20514.3 | K6: COD | L6: Cancelled | P6: =TEXT(B6,"MMM") -> Jul | R6: =IF(J6>5000,"High Sales",IF(J6>2000,"Medium Sales","Low Sales")) -> High Sales | S6: =IF(I6>=20,"High Discount","Low Discount") -> Low Discount | T6: =IF(L6="Delivered","Successful","Pending") -> Pending
A7: FK0006 | B7: 45932 | C7: 1016 | D7: Pune | E7: Keyboard | F7: Accessories | G7: 1 | H7: 48323 | I7: 20 | J7: 38658.4 | K7: UPI | L7: Cancelled | P7: =TEXT(B7,"MMM") -> Oct | R7: =IF(J7>5000,"High Sales",IF(J7>2000,"Medium Sales","Low Sales")) -> High Sales | S7: =IF(I7>=20,"High Discount","Low Discount") -> High Discount | T7: =IF(L7="Delivered","Successful","Pending") -> Pending
A8: FK0007 | B8: 45756 | C8: 1091 | D8: Madurai | E8: Keyboard | F8: Accessories | G8: 5 | H8: 24200 | I8: 25 | J8: 90750 | K8: UPI | L8: Cancelled | P8: =TEXT(B8,"MMM") -> Apr | R8: =IF(J8>5000,"High Sales",IF(J8>2000,"Medium Sales","Low Sales")) -> High Sales | S8: =IF(I8>=20,"High Discount","Low Discount") -> High Discount | T8: =IF(L8="Delivered","Successful","Pending") -> Pending
A9: FK0008 | B9: 45709 | C9: 1049 | D9: Delhi | E9: Smartwatch | F9: Wearables | G9: 3 | H9: 5729 | I9: 10 | J9: 15468.3 | K9: Net Banking | L9: Cancelled | P9: =TEXT(B9,"MMM") -> Feb | R9: =IF(J9>5000,"High Sales",IF(J9>2000,"Medium Sales","Low Sales")) -> High Sales | S9: =IF(I9>=20,"High Discount","Low Discount") -> Low Discount | T9: =IF(L9="Delivered","Successful","Pending") -> Pending
A10: FK0009 | B10: 45765 | C10: 1086 | D10: Delhi | E10: Monitor | F10: Electronics | G10: 2 | H10: 24760 | I10: 15 | J10: 42092 | K10: UPI | L10: Cancelled | P10: =TEXT(B10,"MMM") -> Apr | R10: =IF(J10>5000,"High Sales",IF(J10>2000,"Medium Sales","Low Sales")) -> High Sales | S10: =IF(I10>=20,"High Discount","Low Discount") -> Low Discount | T10: =IF(L10="Delivered","Successful","Pending") -> Pending
A11: FK0010 | B11: 45741 | C11: 1060 | D11: Pune | E11: Headphones | F11: Accessories | G11: 5 | H11: 48284 | I11: 10 | J11: 217278 | K11: COD | L11: Cancelled | P11: =TEXT(B11,"MMM") -> Mar | R11: =IF(J11>5000,"High Sales",IF(J11>2000,"Medium Sales","Low Sales")) -> High Sales | S11: =IF(I11>=20,"High Discount","Low Discount") -> Low Discount | T11: =IF(L11="Delivered","Successful","Pending") -> Pending
A12: FK0011 | B12: 45686 | C12: 1030 | D12: Chennai | E12: T-Shirt | F12: Fashion | G12: 2 | H12: 45366 | I12: 15 | J12: 77122.2 | K12: COD | L12: Pending | P12: =TEXT(B12,"MMM") -> Jan | R12: =IF(J12>5000,"High Sales",IF(J12>2000,"Medium Sales","Low Sales")) -> High Sales | S12: =IF(I12>=20,"High Discount","Low Discount") -> Low Discount | T12: =IF(L12="Delivered","Successful","Pending") -> Pending
A13: FK0012 | B13: 45819 | C13: 1028 | D13: Kolkata | E13: Keyboard | F13: Accessories | G13: 1 | H13: 14326 | I13: 25 | J13: 10744.5 | K13: Net Banking | L13: Cancelled | P13: =TEXT(B13,"MMM") -> Jun | R13: =IF(J13>5000,"High Sales",IF(J13>2000,"Medium Sales","Low Sales")) -> High Sales | S13: =IF(I13>=20,"High Discount","Low Discount") -> High Discount | T13: =IF(L13="Delivered","Successful","Pending") -> Pending
A14: FK0013 | B14: 45784 | C14: 1096 | D14: Delhi | E14: Shoes | F14: Fashion | G14: 2 | H14: 17859 | I14: 10 | J14: 32146.2 | K14: Net Banking | L14: Cancelled | P14: =TEXT(B14,"MMM") -> May | R14: =IF(J14>5000,"High Sales",IF(J14>2000,"Medium Sales","Low Sales")) -> High Sales | S14: =IF(I14>=20,"High Discount","Low Discount") -> Low Discount | T14: =IF(L14="Delivered","Successful","Pending") -> Pending
A15: FK0014 | B15: 45918 | C15: 1064 | D15: Madurai | E15: Camera | F15: Electronics | G15: 3 | H15: 14873 | I15: 10 | J15: 40157.1 | K15: UPI | L15: Delivered | P15: =TEXT(B15,"MMM") -> Sep | R15: =IF(J15>5000,"High Sales",IF(J15>2000,"Medium Sales","Low Sales")) -> High Sales | S15: =IF(I15>=20,"High Discount","Low Discount") -> Low Discount | T15: =IF(L15="Delivered","Successful","Pending") -> Successful
... A201: FK0200 | B201: 45781 | C201: 1074 | D201: Pune | E201: Camera | F201: Electronics | G201: 1 | H201: 40792 | I201: 15 | J201: 34673.2 | K201: Card | L201: Cancelled | P201: =TEXT(B201,"MMM") -> May | R201: =IF(J201>5000,"High Sales",IF(J201>2000,"Medium Sales","Low Sales")) -> High Sales | S201: =IF(I201>=20,"High Discount","Low Discount") -> Low Discount | T201: =IF(L201="Delivered","Successful","Pending") -> Pending

Sheet Overview Analysis
A1: Total Sales | B1: Total Orders | C1: Total Quantity Sold | D1: Average Sales Amount | E1: Maximum Sales Order | F1: Minimum Sales Order | G1: Average discount percentage
A2: =SUM(Flipkart_Sales_Data!J:J) -> 12371153 | B2: =COUNTA(Flipkart_Sales_Data!A:A)-1 -> 200 | C2: =SUM(Flipkart_Sales_Data!G:G) -> 593 | D2: =AVERAGE(Flipkart_Sales_Data!J:J) -> 61855.764 | E2: =MAX(Flipkart_Sales_Data!J:J) -> 235201 | F2: =MIN(Flipkart_Sales_Data!J:J) -> 804.8 | G2: =AVERAGE(Flipkart_Sales_Data!I:I) -> 14.525

Sheet Dashboard
